{
  "updated": "2026-07-11 21:02",
  "data": {
    "Empress": {
      "2026-07-11": {
        "sold": []
      },
      "2026-07-12": {
        "sold": []
      },
      "2026-07-13": {
        "sold": []
      },
      "2026-07-14": {
        "sold": []
      },
      "2026-07-15": {
        "sold": []
      },
      "2026-07-16": {
        "sold": []
      },
      "2026-07-17": {
        "sold": []
      },
      "2026-07-18": {
        "sold": []
      },
      "2026-07-19": {
        "sold": []
      },
      "2026-07-20": {
        "sold": []
      },
      "2026-07-21": {
        "sold": []
      },
      "2026-07-22": {
        "sold": []
      },
      "2026-07-23": {
        "sold": []
      },
      "2026-07-24": {
        "sold": []
      }
    },
    "Grand Canyon": {
      "2026-07-11": {
        "sold": []
      },
      "2026-07-12": {
        "sold": []
      },
      "2026-07-13": {
        "sold": []
      },
      "2026-07-14": {
        "sold": []
      },
      "2026-07-15": {
        "sold": []
      },
      "2026-07-16": {
        "sold": []
      },
      "2026-07-17": {
        "sold": []
      },
      "2026-07-18": {
        "sold": []
      },
      "2026-07-19": {
        "sold": []
      },
      "2026-07-20": {
        "sold": []
      },
      "2026-07-21": {
        "sold": []
      },
      "2026-07-22": {
        "sold": []
      },
      "2026-07-23": {
        "sold": []
      },
      "2026-07-24": {
        "sold": []
      }
    },
    "Narrow Neck": {
      "2026-07-11": {
        "sold": []
      },
      "2026-07-12": {
        "sold": []
      },
      "2026-07-13": {
        "sold": []
      },
      "2026-07-14": {
        "sold": []
      },
      "2026-07-15": {
        "sold": []
      },
      "2026-07-16": {
        "sold": []
      },
      "2026-07-17": {
        "sold": []
      },
      "2026-07-18": {
        "sold": []
      },
      "2026-07-19": {
        "sold": []
      },
      "2026-07-20": {
        "sold": []
      },
      "2026-07-21": {
        "sold": []
      },
      "2026-07-22": {
        "sold": []
      },
      "2026-07-23": {
        "sold": []
      },
      "2026-07-24": {
        "sold": [
          {
            "time": "2026-07-24T09:00:00",
            "company": "High n Wild"
          }
        ]
      }
    }
  }
}